qprof/__init__.py
qprof/input_data.py
qprof/models.py
qprof/qprof.py
qprof/data/gprof_gmi_normalizer.pckl
qprof/data/qrnn_gmi_3_256_relu.pt
qprof/file_formats/__init__.py
qprof/file_formats/bin.py
qprof/file_formats/preprocessor.py
qprof/file_formats/retrieval.py
gpm_qprof-0.0.1.dev0.dist-info/LICENSE
gpm_qprof-0.0.1.dev0.dist-info/METADATA
gpm_qprof-0.0.1.dev0.dist-info/WHEEL
gpm_qprof-0.0.1.dev0.dist-info/entry_points.txt
gpm_qprof-0.0.1.dev0.dist-info/top_level.txt
gpm_qprof-0.0.1.dev0.dist-info/RECORD
